{"cameraMode":{"drawMode":0,"name":"Shaded","section":"Shading Mode"},"sceneLighting":false,"audioPlay":false,"sceneViewState":{"m_AlwaysRefresh":false,"showFog":true,"showSkybox":false,"showFlares":true,"showImageEffects":true,"showParticleSystems":true,"showVisualEffectGraphs":true,"m_FxEnabled":true},"in2DMode":false,"pivot":{"x":-25.70911407470703,"y":0.013734430074691773,"z":36.49074172973633},"rotation":{"x":0.12801271677017213,"y":0.2928580641746521,"z":-0.039594706147909167,"w":0.9467307925224304},"size":0.24494849145412446,"orthographic":false}